aiocallback/__init__.py
aiocallback/__version__.py
aiocallback/events.py
aiocallback/py.typed
aiocallback-0.1.9.dist-info/licenses/LICENSE
aiocallback-0.1.9.dist-info/METADATA
aiocallback-0.1.9.dist-info/WHEEL
aiocallback-0.1.9.dist-info/top_level.txt
aiocallback-0.1.9.dist-info/RECORD
