Metadata-Version: 2.4
Name: aiocallback
Version: 0.1.9
Summary: A library for helping configure asynchronous callbacks using member descriptors
Author-email: Vizonex <VizonexBusiness@gmail.com>
Project-URL: homepage, https://github.com/Vizonex/aiocallback
Project-URL: repository, https://github.com/Vizonex/aiocallback.git
Keywords: event callbacks,callbacks,asyncio
Classifier: Framework :: AsyncIO
Classifier: Intended Audience :: Developers
Classifier: Topic :: Software Development :: Libraries
Classifier: Programming Language :: Python :: 3.9
Classifier: Programming Language :: Python :: 3.10
Classifier: Programming Language :: Python :: 3.11
Classifier: Programming Language :: Python :: 3.12
Classifier: Programming Language :: Python :: 3.13
Requires-Python: >=3.9
License-File: LICENSE
Requires-Dist: frozenlist
Requires-Dist: typing-extensions; python_version < "3.10"
Requires-Dist: propcache>=0.3.2
Dynamic: license-file
